{
    "Weeks": [
      {
        "Week": "February 24 - March 2",
        "Schedule": [
          {"Day": "MON", "Date": "24-02", "Throwing": "Pitch", "Lifting": "Conditioning A", "Game": "Cinco Ranch (Away) 6:30pm"},
          {"Day": "TUE", "Date": "25-02", "Throwing": "Tolerance", "Lifting": "Lower A", "Game": ""},
          {"Day": "WED", "Date": "26-02", "Throwing": "Flat Ground", "Lifting": "Upper A", "Game": ""},
          {"Day": "THU", "Date": "27-02", "Throwing": "Tolerance", "Lifting": "Conditioning B", "Game": ""},
          {"Day": "FRI", "Date": "28-02", "Throwing": "Bullpen", "Lifting": "Lower B OR Upper B", "Game": ""},
          {"Day": "SAT", "Date": "29-02", "Throwing": "Tolerance", "Lifting": "Upper B OR Conditioning A", "Game": ""},
          {"Day": "SUN", "Date": "1-03", "Throwing": "Light Flat Ground", "Lifting": "OFF", "Game": ""}
        ]
      },
      {
        "Week": "March 3 - March 9",
        "Schedule": [
          {"Day": "MON", "Date": "3-03", "Throwing": "Pitch", "Lifting": "Conditioning A", "Game": "Cinco Ranch (Home) 6:30pm"},
          {"Day": "TUE", "Date": "4-03", "Throwing": "Tolerance", "Lifting": "Lower A", "Game": ""},
          {"Day": "WED", "Date": "5-03", "Throwing": "Flat Ground", "Lifting": "Upper A", "Game": ""},
          {"Day": "THU", "Date": "6-03", "Throwing": "Tolerance", "Lifting": "Conditioning B", "Game": ""},
          {"Day": "FRI", "Date": "7-03", "Throwing": "Bullpen", "Lifting": "Lower B OR Upper B", "Game": ""},
          {"Day": "SAT", "Date": "8-03", "Throwing": "Tolerance", "Lifting": "Upper B OR Conditioning A", "Game": ""},
          {"Day": "SUN", "Date": "9-03", "Throwing": "Light Flat Ground", "Lifting": "OFF", "Game": ""}
        ]
      },
      {
        "Week": "March 10 - March 16",
        "Schedule": [
          {"Day": "MON", "Date": "10-03", "Throwing": "Bullpen", "Lifting": "Lower B OR Upper B", "Game": ""},
          {"Day": "TUE", "Date": "11-03", "Throwing": "Light Flat Ground", "Lifting": "Upper B OR Conditioning A", "Game": ""},
          {"Day": "WED", "Date": "12-03", "Throwing": "Pitch", "Lifting": "Conditioning A", "Game": "Freeman (Home) 12/2:15"},
          {"Day": "THU", "Date": "13-03", "Throwing": "Tolerance", "Lifting": "Lower A", "Game": ""},
          {"Day": "FRI", "Date": "14-03", "Throwing": "Flat Ground", "Lifting": "Upper A", "Game": ""},
          {"Day": "SAT", "Date": "15-03", "Throwing": "Tolerance", "Lifting": "Conditioning B", "Game": ""},
          {"Day": "SUN", "Date": "16-03", "Throwing": "Light Flat Ground", "Lifting": "OFF", "Game": ""}
        ]
      },
      {
        "Week": "March 17 - March 23",
        "Schedule": [
          {"Day": "MON", "Date": "17-03", "Throwing": "Bullpen", "Lifting": "Lower B OR Upper B", "Game": ""},
          {"Day": "TUE", "Date": "18-03", "Throwing": "Light Flat Ground", "Lifting": "Upper B OR Conditioning A", "Game": ""},
          {"Day": "WED", "Date": "19-03", "Throwing": "Pitch", "Lifting": "Conditioning A", "Game": "Katy (Home) 4/6:30"},
          {"Day": "THU", "Date": "20-03", "Throwing": "Tolerance", "Lifting": "Lower A", "Game": ""},
          {"Day": "FRI", "Date": "21-03", "Throwing": "Flat Ground", "Lifting": "Upper A", "Game": ""},
          {"Day": "SAT", "Date": "22-03", "Throwing": "Tolerance", "Lifting": "Conditioning B", "Game": ""},
          {"Day": "SUN", "Date": "23-03", "Throwing": "Light Flat Ground", "Lifting": "OFF", "Game": ""}
        ]
      },
      {
        "Week": "March 24 - March 30",
        "Schedule": [
          {"Day": "MON", "Date": "24-03", "Throwing": "Bullpen", "Lifting": "Lower B OR Upper B", "Game": ""},
          {"Day": "TUE", "Date": "25-03", "Throwing": "Light Flat Ground", "Lifting": "Upper B OR Conditioning A", "Game": ""},
          {"Day": "WED", "Date": "26-03", "Throwing": "Pitch", "Lifting": "Conditioning A", "Game": "Taylor (Away) 4/6:30"},
          {"Day": "THU", "Date": "27-03", "Throwing": "Tolerance", "Lifting": "Lower A", "Game": ""},
          {"Day": "FRI", "Date": "28-03", "Throwing": "Flat Ground", "Lifting": "Upper A", "Game": ""},
          {"Day": "SAT", "Date": "29-03", "Throwing": "Tolerance", "Lifting": "Conditioning B", "Game": ""},
          {"Day": "SUN", "Date": "30-03", "Throwing": "Light Flat Ground", "Lifting": "OFF", "Game": ""}
        ]
      },
      {
        "Week": "March 31 - April 6",
        "Schedule": [
          {"Day": "MON", "Date": "31-03", "Throwing": "Bullpen", "Lifting": "Lower B OR Upper B", "Game": ""},
          {"Day": "TUE", "Date": "1-04", "Throwing": "Light Flat Ground", "Lifting": "Upper B OR Conditioning A", "Game": ""},
          {"Day": "WED", "Date": "2-04", "Throwing": "Pitch", "Lifting": "Conditioning A", "Game": "Jordan (Home) 4/6:30"},
          {"Day": "THU", "Date": "3-04", "Throwing": "Tolerance", "Lifting": "Lower A", "Game": ""},
          {"Day": "FRI", "Date": "4-04", "Throwing": "Tolerance", "Lifting": "Conditioning B", "Game": ""},
          {"Day": "SAT", "Date": "5-04", "Throwing": "Pitch", "Lifting": "Conditioning A", "Game": "Paetow (Away) 12/2:15"},
          {"Day": "SUN", "Date": "6-04", "Throwing": "Light Flat Ground", "Lifting": "OFF", "Game": ""}
        ]
      },
      {
        "Week": "April 7 - April 13",
        "Schedule": [
          {"Day": "MON", "Date": "7-04", "Throwing": "Tolerance", "Lifting": "Lower A", "Game": ""},
          {"Day": "TUE", "Date": "8-04", "Throwing": "Flat Ground", "Lifting": "Upper A", "Game": ""},
          {"Day": "WED", "Date": "9-04", "Throwing": "Bullpen", "Lifting": "Lower B OR Upper B", "Game": ""},
          {"Day": "THU", "Date": "10-04", "Throwing": "Pitch", "Lifting": "Conditioning A", "Game": "Tompkins (Home) 4/6:30"},
          {"Day": "FRI", "Date": "11-04", "Throwing": "Tolerance", "Lifting": "Lower A", "Game": ""},
          {"Day": "SAT", "Date": "12-04", "Throwing": "Flat Ground", "Lifting": "Upper A", "Game": ""},
          {"Day": "SUN", "Date": "13-04", "Throwing": "Light Flat Ground", "Lifting": "OFF", "Game": ""}
        ]
      },
      {
        "Week": "April 14 - April 20",
        "Schedule": [
          {"Day": "MON", "Date": "14-04", "Throwing": "Tolerance", "Lifting": "Conditioning B", "Game": ""},
          {"Day": "TUE", "Date": "15-04", "Throwing": "Bullpen", "Lifting": "Lower B OR Upper B", "Game": ""},
          {"Day": "WED", "Date": "16-04", "Throwing": "Pitch", "Lifting": "Conditioning A", "Game": "Mayde Creek (Away) 4/6:30"},
          {"Day": "THU", "Date": "17-04", "Throwing": "Tolerance", "Lifting": "Lower A", "Game": ""},
          {"Day": "FRI", "Date": "18-04", "Throwing": "Flat Ground", "Lifting": "Upper A", "Game": ""},
          {"Day": "SAT", "Date": "19-04", "Throwing": "Tolerance", "Lifting": "Conditioning B", "Game": ""},
          {"Day": "SUN", "Date": "20-04", "Throwing": "Light Flat Ground", "Lifting": "OFF", "Game": ""}
        ]
      },
      {
        "Week": "April 21 - April 27",
        "Schedule": [
          {"Day": "MON", "Date": "21-04", "Throwing": "Bullpen", "Lifting": "Lower B OR Upper B", "Game": ""},
          {"Day": "TUE", "Date": "22-04", "Throwing": "Light Flat Ground", "Lifting": "Upper B OR Conditioning A", "Game": ""},
          {"Day": "WED", "Date": "23-04", "Throwing": "Tolerance", "Lifting": "Lower A", "Game": ""},
          {"Day": "THU", "Date": "24-04", "Throwing": "Pitch", "Lifting": "Conditioning A", "Game": "Morton Ranch (Home) 4/6:30"},
          {"Day": "FRI", "Date": "25-04", "Throwing": "Tolerance", "Lifting": "Lower A", "Game": ""},
          {"Day": "SAT", "Date": "26-04", "Throwing": "Flat Ground", "Lifting": "Upper A", "Game": ""},
          {"Day": "SUN", "Date": "27-04", "Throwing": "Light Flat Ground", "Lifting": "OFF", "Game": ""}
        ]
      }
    ]

}
